{
    "key": "group_62a92aed40529",
    "title": "Contest",
    "fields": [
        {
            "key": "field_62a92cf8bfae9",
            "label": "Project Title",
            "name": "project_title",
            "type": "text",
            "instructions": "",
            "required": 0,
            "conditional_logic": 0,
            "wrapper": {
                "width": "",
                "class": "",
                "id": ""
            },
            "default_value": "",
            "placeholder": "",
            "prepend": "",
            "append": "",
            "maxlength": ""
        },
        {
            "key": "field_62a92cc0bfae8",
            "label": "Project Type",
            "name": "project_type",
            "type": "select",
            "instructions": "",
            "required": 0,
            "conditional_logic": 0,
            "wrapper": {
                "width": "",
                "class": "",
                "id": ""
            },
            "choices": {
                "Commercial": "Commercial",
                "Social Impact": "Social Impact",
                "Artistic": "Artistic",
                "Education": "Education"
            },
            "default_value": [],
            "allow_null": 0,
            "multiple": 1,
            "ui": 0,
            "return_format": "value",
            "ajax": 0,
            "placeholder": ""
        },
        {
            "key": "field_62a92c67bfae4",
            "label": "Project Video Link",
            "name": "project_video_link",
            "type": "text",
            "instructions": "",
            "required": 0,
            "conditional_logic": 0,
            "wrapper": {
                "width": "",
                "class": "",
                "id": ""
            },
            "default_value": "",
            "placeholder": "",
            "prepend": "",
            "append": "",
            "maxlength": ""
        },
        {
            "key": "field_62a92c9ebfae6",
            "label": "Project URL",
            "name": "project_url",
            "type": "text",
            "instructions": "",
            "required": 0,
            "conditional_logic": 0,
            "wrapper": {
                "width": "",
                "class": "",
                "id": ""
            },
            "default_value": "",
            "placeholder": "",
            "prepend": "",
            "append": "",
            "maxlength": ""
        },
        {
            "key": "field_62a92cafbfae7",
            "label": "Short Description",
            "name": "project_short_description",
            "type": "text",
            "instructions": "",
            "required": 0,
            "conditional_logic": 0,
            "wrapper": {
                "width": "",
                "class": "",
                "id": ""
            },
            "default_value": "",
            "placeholder": "",
            "prepend": "",
            "append": "",
            "maxlength": ""
        },
        {
            "key": "field_62a92c7abfae5",
            "label": "Project Photos",
            "name": "project_photos",
            "type": "repeater",
            "instructions": "",
            "required": 0,
            "conditional_logic": 0,
            "wrapper": {
                "width": "",
                "class": "",
                "id": ""
            },
            "collapsed": "",
            "min": 0,
            "max": 0,
            "layout": "table",
            "button_label": "",
            "sub_fields": [
                {
                    "key": "field_62aa0d0f3f578",
                    "label": "Photo URL",
                    "name": "photo_url",
                    "type": "text",
                    "instructions": "",
                    "required": 0,
                    "conditional_logic": 0,
                    "wrapper": {
                        "width": "",
                        "class": "",
                        "id": ""
                    },
                    "default_value": "",
                    "placeholder": "",
                    "prepend": "",
                    "append": "",
                    "maxlength": ""
                }
            ]
        },
        {
            "key": "field_62a92be3bfae0",
            "label": "What impact does your project have on others as well as yourself?",
            "name": "project_import",
            "type": "textarea",
            "instructions": "",
            "required": 0,
            "conditional_logic": 0,
            "wrapper": {
                "width": "",
                "class": "",
                "id": ""
            },
            "default_value": "",
            "placeholder": "",
            "maxlength": "",
            "rows": "",
            "new_lines": ""
        },
        {
            "key": "field_62a92bf3bfae1",
            "label": "What did you learn by doing this project?",
            "name": "what_did_you_learn",
            "type": "textarea",
            "instructions": "",
            "required": 0,
            "conditional_logic": 0,
            "wrapper": {
                "width": "",
                "class": "",
                "id": ""
            },
            "default_value": "",
            "placeholder": "",
            "maxlength": "",
            "rows": "",
            "new_lines": ""
        },
        {
            "key": "field_62a92c22bfae2",
            "label": "What is your project about and how does it work?",
            "name": "what_is_project_about",
            "type": "textarea",
            "instructions": "",
            "required": 0,
            "conditional_logic": 0,
            "wrapper": {
                "width": "",
                "class": "",
                "id": ""
            },
            "default_value": "",
            "placeholder": "",
            "maxlength": "",
            "rows": "",
            "new_lines": ""
        },
        {
            "key": "field_62a92c47bfae3",
            "label": "What inspired you or what is the idea that got you started?",
            "name": "inspiration",
            "type": "textarea",
            "instructions": "",
            "required": 0,
            "conditional_logic": 0,
            "wrapper": {
                "width": "",
                "class": "",
                "id": ""
            },
            "default_value": "",
            "placeholder": "",
            "maxlength": "",
            "rows": "",
            "new_lines": ""
        },
        {
            "key": "field_62a92d08bfaea",
            "label": "TikTok",
            "name": "tiktok_url",
            "type": "text",
            "instructions": "",
            "required": 0,
            "conditional_logic": 0,
            "wrapper": {
                "width": "",
                "class": "",
                "id": ""
            },
            "default_value": "",
            "placeholder": "",
            "prepend": "",
            "append": "",
            "maxlength": ""
        },
        {
            "key": "field_62a92d12bfaeb",
            "label": "YouTube",
            "name": "youtube_url",
            "type": "text",
            "instructions": "",
            "required": 0,
            "conditional_logic": 0,
            "wrapper": {
                "width": "",
                "class": "",
                "id": ""
            },
            "default_value": "",
            "placeholder": "",
            "prepend": "",
            "append": "",
            "maxlength": ""
        },
        {
            "key": "field_62a92d2ebfaec",
            "label": "Twitter",
            "name": "twitter_url",
            "type": "text",
            "instructions": "",
            "required": 0,
            "conditional_logic": 0,
            "wrapper": {
                "width": "",
                "class": "",
                "id": ""
            },
            "default_value": "",
            "placeholder": "",
            "prepend": "",
            "append": "",
            "maxlength": ""
        },
        {
            "key": "field_62a92d3ebfaed",
            "label": "Facebook",
            "name": "facebook_url",
            "type": "text",
            "instructions": "",
            "required": 0,
            "conditional_logic": 0,
            "wrapper": {
                "width": "",
                "class": "",
                "id": ""
            },
            "default_value": "",
            "placeholder": "",
            "prepend": "",
            "append": "",
            "maxlength": ""
        },
        {
            "key": "field_62a92d50bfaee",
            "label": "Instagram",
            "name": "instagram_url",
            "type": "text",
            "instructions": "",
            "required": 0,
            "conditional_logic": 0,
            "wrapper": {
                "width": "",
                "class": "",
                "id": ""
            },
            "default_value": "",
            "placeholder": "",
            "prepend": "",
            "append": "",
            "maxlength": ""
        },
        {
            "key": "field_62a92d84bfaf1",
            "label": "Affiliation",
            "name": "affiliation",
            "type": "select",
            "instructions": "",
            "required": 0,
            "conditional_logic": 0,
            "wrapper": {
                "width": "",
                "class": "",
                "id": ""
            },
            "choices": {
                "Makerspace": "Makerspace",
                "School": "School",
                "Company": "Company",
                "Club": "Club",
                "None": "None",
                "Other": "Other"
            },
            "default_value": false,
            "allow_null": 0,
            "multiple": 0,
            "ui": 0,
            "return_format": "value",
            "ajax": 0,
            "placeholder": ""
        },
        {
            "key": "field_62a92d71bfaf0",
            "label": "Other Affiliation",
            "name": "other_affiliation",
            "type": "text",
            "instructions": "",
            "required": 0,
            "conditional_logic": 0,
            "wrapper": {
                "width": "",
                "class": "",
                "id": ""
            },
            "default_value": "",
            "placeholder": "",
            "prepend": "",
            "append": "",
            "maxlength": ""
        },
        {
            "key": "field_62a92af1bfad5",
            "label": "Affiliation Text",
            "name": "affiliation_text",
            "type": "text",
            "instructions": "",
            "required": 0,
            "conditional_logic": 0,
            "wrapper": {
                "width": "",
                "class": "",
                "id": ""
            },
            "default_value": "",
            "placeholder": "",
            "prepend": "",
            "append": "",
            "maxlength": ""
        },
        {
            "key": "field_62a92e2dbfaf9",
            "label": "First Name",
            "name": "first_name",
            "type": "text",
            "instructions": "",
            "required": 0,
            "conditional_logic": 0,
            "wrapper": {
                "width": "",
                "class": "",
                "id": ""
            },
            "default_value": "",
            "placeholder": "",
            "prepend": "",
            "append": "",
            "maxlength": ""
        },
        {
            "key": "field_62a92e1cbfaf8",
            "label": "Last Name",
            "name": "last_name",
            "type": "text",
            "instructions": "",
            "required": 0,
            "conditional_logic": 0,
            "wrapper": {
                "width": "",
                "class": "",
                "id": ""
            },
            "default_value": "",
            "placeholder": "",
            "prepend": "",
            "append": "",
            "maxlength": ""
        },
        {
            "key": "field_62a92e3fbfafa",
            "label": "Email Address",
            "name": "user_email",
            "type": "text",
            "instructions": "",
            "required": 0,
            "conditional_logic": 0,
            "wrapper": {
                "width": "",
                "class": "",
                "id": ""
            },
            "default_value": "",
            "placeholder": "",
            "prepend": "",
            "append": "",
            "maxlength": ""
        },
        {
            "key": "field_62a92dfabfaf7",
            "label": "Age Group",
            "name": "age_group",
            "type": "select",
            "instructions": "",
            "required": 0,
            "conditional_logic": 0,
            "wrapper": {
                "width": "",
                "class": "",
                "id": ""
            },
            "choices": {
                "Young Maker (13-17)": "Young Maker (13-17)",
                "Maker (18+)": "Maker (18+)"
            },
            "default_value": false,
            "allow_null": 0,
            "multiple": 0,
            "ui": 0,
            "return_format": "value",
            "ajax": 0,
            "placeholder": ""
        },
        {
            "key": "field_62a92daebfaf2",
            "label": "Upload Profile Photo",
            "name": "upload_profile_photo",
            "type": "text",
            "instructions": "",
            "required": 0,
            "conditional_logic": 0,
            "wrapper": {
                "width": "",
                "class": "",
                "id": ""
            },
            "default_value": "",
            "placeholder": "",
            "prepend": "",
            "append": "",
            "maxlength": ""
        },
        {
            "key": "field_62a92debbfaf6",
            "label": "Address",
            "name": "user_address",
            "type": "text",
            "instructions": "",
            "required": 0,
            "conditional_logic": 0,
            "wrapper": {
                "width": "",
                "class": "",
                "id": ""
            },
            "default_value": "",
            "placeholder": "",
            "prepend": "",
            "append": "",
            "maxlength": ""
        },
        {
            "key": "field_62a92de0bfaf5",
            "label": "City",
            "name": "user_city",
            "type": "text",
            "instructions": "",
            "required": 0,
            "conditional_logic": 0,
            "wrapper": {
                "width": "",
                "class": "",
                "id": ""
            },
            "default_value": "",
            "placeholder": "",
            "prepend": "",
            "append": "",
            "maxlength": ""
        },
        {
            "key": "field_62a92dd1bfaf4",
            "label": "State \/ Province \/ Region",
            "name": "user_state",
            "type": "text",
            "instructions": "",
            "required": 0,
            "conditional_logic": 0,
            "wrapper": {
                "width": "",
                "class": "",
                "id": ""
            },
            "default_value": "",
            "placeholder": "",
            "prepend": "",
            "append": "",
            "maxlength": ""
        },
        {
            "key": "field_62a92dc4bfaf3",
            "label": "Country",
            "name": "user_country",
            "type": "text",
            "instructions": "",
            "required": 0,
            "conditional_logic": 0,
            "wrapper": {
                "width": "",
                "class": "",
                "id": ""
            },
            "default_value": "",
            "placeholder": "",
            "prepend": "",
            "append": "",
            "maxlength": ""
        },
        {
            "key": "field_62a92d60bfaef",
            "label": "Tell Us About Yourself",
            "name": "user_about",
            "type": "text",
            "instructions": "",
            "required": 0,
            "conditional_logic": 0,
            "wrapper": {
                "width": "",
                "class": "",
                "id": ""
            },
            "default_value": "",
            "placeholder": "",
            "prepend": "",
            "append": "",
            "maxlength": ""
        },
        {
            "key": "field_62a92b1fbfad6",
            "label": "Team Members",
            "name": "team_members",
            "type": "textarea",
            "instructions": "",
            "required": 0,
            "conditional_logic": 0,
            "wrapper": {
                "width": "",
                "class": "",
                "id": ""
            },
            "default_value": "",
            "placeholder": "",
            "maxlength": "",
            "rows": "",
            "new_lines": ""
        },
        {
            "key": "field_62aa166cd980d",
            "label": "Zip Code",
            "name": "user_zip",
            "type": "text",
            "instructions": "",
            "required": 0,
            "conditional_logic": 0,
            "wrapper": {
                "width": "",
                "class": "",
                "id": ""
            },
            "default_value": "",
            "placeholder": "",
            "prepend": "",
            "append": "",
            "maxlength": ""
        }
    ],
    "location": [
        [
            {
                "param": "post_type",
                "operator": "==",
                "value": "contestants"
            }
        ]
    ],
    "menu_order": 0,
    "position": "normal",
    "style": "default",
    "label_placement": "top",
    "instruction_placement": "label",
    "hide_on_screen": "",
    "active": true,
    "description": "",
    "show_in_rest": 0,
    "modified": 1655314060
}